TERNData/__init__.py
TERNData/auscover.py
TERNData/constants.py
TERNData/node.py
TERNData/ozflux.py
TERNData/tree.py
TERNData/utils.py
terndata-0.0.4.dist-info/DESCRIPTION.rst
terndata-0.0.4.dist-info/METADATA
terndata-0.0.4.dist-info/RECORD
terndata-0.0.4.dist-info/WHEEL
terndata-0.0.4.dist-info/metadata.json
terndata-0.0.4.dist-info/top_level.txt
