Metadata-Version: 2.0
Name: terndata
Version: 0.0.4
Summary: A python module to access TERN dap data
Home-page: UNKNOWN
Author: yi sun
Author-email: y.sun5@uq.edu.au
License: UNKNOWN
Keywords: access TERN data
Platform: UNKNOWN
Requires-Dist: XlsxWriter
Requires-Dist: netCDF4
Requires-Dist: numpy
Requires-Dist: pandas
Requires-Dist: thredds-crawler
